linepost/__init__.py
linepost/line.py
linepost/line_test.py
linepost/position.py
linepost/position_test.py
linepost/repertoire.py
linepost/repertoire_test.py
linepost/visual.py
linepost-0.1.0.dist-info/METADATA
linepost-0.1.0.dist-info/WHEEL
linepost-0.1.0.dist-info/licenses/LICENSE
linepost-0.1.0.dist-info/RECORD
