Metadata-Version: 2.1
Name: linepost
Version: 0.1.0
Summary: Chess opening visualization library
Project-URL: Homepage, https://github.com/jcraver1021/chess-opening-layout
Project-URL: Bug Tracker, https://github.com/jcraver1021/chess-opening-layout/issues
Author: James Craver
License-File: LICENSE
Classifier: License :: OSI Approved :: MIT License
Classifier: Programming Language :: Python :: 3
Requires-Python: >=3.7
